typ/__init__.py
typ/encoding.py
typ/json.py
typ/types/__init__.py
typ/types/union.py
typjson-0.0.32.dist-info/WHEEL
typjson-0.0.32.dist-info/METADATA
typjson-0.0.32.dist-info/RECORD
